datawiserai/__init__.py
datawiserai-0.0.1.dist-info/METADATA
datawiserai-0.0.1.dist-info/WHEEL
datawiserai-0.0.1.dist-info/RECORD
