Metadata-Version: 2.4
Name: datawiserai
Version: 0.0.1
Summary: Official Python client for the Datawiser API (placeholder package).
Project-URL: Homepage, https://datawiser.ai
Project-URL: Documentation, https://datawiser.ai/api
Project-URL: Source, https://github.com/datawiserai/python-client
Author-email: Datawiser <founder@datawiser.ai>
License: Proprietary
Requires-Python: >=3.9
